Workbook
Name ProcessNodeShape: [1]TreePlanXLM!$B$254
Name RT: 999999999999
Name WatermarkBranding: [1]TreePlanXLM!$B$607

Sheet Instructions
B2: Tasks
B4: The purpose of this seminar is to test your understanding of decision analysis concepts.
B5: The examples (GymFit and Acme company) are drawn from Topic 6: Decision Analysis lecture slides.
D7: GymFit 1 worksheet
C10: 1 | D10: GymFit 2 worksheet
D11: Show how EMV is applied to determine the best decision alternative for GymFit.
C13: 2 | D13: GymFit 3 worksheet
D14: Find the EVPI for Gymfit, and explain how it is can be used by GymFit management team to determine the value of information.
C16: 3 | D16: Acme 1 worksheet
D17: Slide 20 presents a one-stage decision problem for Acme Company.
D18: Determine whether Acme should proceed with developing the new product.
C20: 4 | D20: Acme 2 worksheet
D21: Perform the EMV calculations given on slide 24 and write down the best strategy for Acme.
C23: 5 | D23: Acme 3 worksheet
D24: Show how the probabilities are determined in the risk profile of the best decisions for Acme's two-stage decision problem (lecture slide 25).

Sheet GymFit 1
B2: Gymfit Case study
B3: In order to expand GymFit’s business, management intends to build a new fitness centre and is trying to determine what type of facility to build. Only two types are under consideration: Fitness Centre and Fitness Centre with Aquatic facilities. i.e. the following decision alternatives are available to management:
E4: Decision alternatives
E6: 1 | F6: Build a Fitness Centre with Aquatic facilities
B7: - | C7: Decision alternative 1: Build a Fitness Centre with Aquatic facilities | E7: 2 | F7: Build a Fitness Centre
B8: - | C8: Decision alternative 2: Build a Fitness Centre | E8: 3 | F8: Build nothing (keep their business at its current size)
B9: - | C9: Decision alternative 3: Build nothing (keep their business at its current size).
B11: GymFit determines that all three of its decision have the same three possible outcomes:
B12: - | C12: Outcome 1: Strong demand for facilities
B13: - | C13: Outcome 2: Moderate demand for facilities | E13: Possible outcomes
B14: - | C14: Outcome 3: Weak demand for facilities.
E15: 1 | F15: Strong demand for facilities
B16: Management believes that: | E16: 2 | F16: Moderate demand for facilities
B17: - | C17: a Fitness Centre with Aquatic facilities would produce a net profit of $80k, $40k, or a net loss of $60k if demand was strong, moderate, or weak respectively | E17: 3 | F17: Weak demand for facilities
B20: - | C20: a Fitness Centre would produce net profits of $45k, $25k, or a net loss of $10k if demand was strong, moderate, or weak respectively
E21: Complete the following table
B23: - | C23: building nothing would result in a net profit of $10k, $5k and $0 if demand was strong, moderate and weak respectively. | F23: Decision Alternatives | G23: Outcomes (Demand for a new facility)
G24: Strong | H24: Moderate | I24: Weak
F25: Build a Fitness Centre with aquatics facilities | G25: 80000 | H25: 40000 | I25: -60000
F26: Build a Fitness Centre | G26: 45000 | H26: 25000 | I26: -10000
F27: Keep their business at its current size | G27: 10000 | H27: 5000 | I27: 0

Sheet GymFit 2
B2: GymFit management assigns the following probabilities to the possible outcomes
D4: Outcomes (Demand for a new facility)
D5: Strong | E5: Moderate | F5: Weak
B6: Probability | D6: 0.2 | E6: 0.5 | F6: 0.3
B9: Task 2. Find the best decision alternative for GymFit (the alternative with the largest expected monetary value)
B11: Decision Alternatives | D11: Outcomes (Demand for a new facility) | G11: EMV for each Decision Alternative
D12: Strong | E12: Moderate | F12: Weak
B13: Build a Fitness Centre with aquatics facilities | D13: ='GymFit 1'!G25 -> 80000 | E13: ='GymFit 1'!H25 -> 40000 | F13: ='GymFit 1'!I25 -> -60000 | H13: Use SUMPRODUCT function to compute EMVs for each decision alternative.
B14: Build a Fitness Centre | D14: ='GymFit 1'!G26 -> 45000 | E14: ='GymFit 1'!H26 -> 25000 | F14: ='GymFit 1'!I26 -> -10000
B15: Keep their business at its current size | D15: ='GymFit 1'!G27 -> 10000 | E15: ='GymFit 1'!H27 -> 5000 | F15: ='GymFit 1'!I27 -> 0

Sheet GymFit 3
B2: A marketing research company claims that for $20,000 it can provide perfect information as to whether demand for new facilities including Fitness and aquatic centre will be strong, moderate or weak.
B4: Task 3. Is the new information worth $20,000? If not, what is the most that GymFit management should be willing to pay for perfect information?
B7: Decision Alternatives | D7: Outcomes (Demand for a new facility) | G7: EMV for each Decision Alternative
D8: Strong | E8: Moderate | F8: Weak
B9: Build a Fitness Centre with aquatics facilities | D9: ='GymFit 2'!D13 -> 80000 | E9: ='GymFit 2'!E13 -> 40000 | F9: ='GymFit 2'!F13 -> -60000 | G9: ='GymFit 2'!G13 -> 0
B10: Build a Fitness Centre | D10: ='GymFit 2'!D14 -> 45000 | E10: ='GymFit 2'!E14 -> 25000 | F10: ='GymFit 2'!F14 -> -10000 | G10: ='GymFit 2'!G14 -> 0
B11: Keep their business at its current size | D11: ='GymFit 2'!D15 -> 10000 | E11: ='GymFit 2'!E15 -> 5000 | F11: ='GymFit 2'!F15 -> 0 | G11: ='GymFit 2'!G15 -> 0
B12: Probability | D12: ='GymFit 2'!D6 -> 0.2 | E12: ='GymFit 2'!E6 -> 0.5 | F12: ='GymFit 2'!F6 -> 0.3
B13: Best payoff of each outcome | G13: Use MAX function identify the best payoff of each outcome.
B15: EMV with perfect information (EMV with PI) | E15: Use SUMPRODUCT function to compute EMV with PI.
B16: EMV without perfect information (EMV without PI) | E16: Use MAX function to find the maximum EMV across the decision alternatives
B17: Expected Value of Perfect Information (EVPI) | E17: EVPI = EMV with PI - EMV without PI

Sheet Acme 1
B1: Acme's single-stage new product decision (lecture slide 20)
B3: Background
B4: Acme Company is trying to decide whether to market a new product.
B5: They are currently part way through developing the product.
B6: If they decide to continue development they will incur a fixed cost of $6 million. | K6: Decision Tree (lecture slide 21) | R6: Net revenue
B7: If the product is marketed its unit margin will be $18.
B9: Fixed cost | C9: 6000000 | O9: Expected
B10: Unit margin | C10: 18 | O10: net revenue
B12: Possible outcomes are ‘great’, ‘fair’, ‘awful’ with estimated sales volumes (in 1,000s) 600, 300, 90 resp. | R12: Net revenue
B13: Probabilities of outcomes are estimated to be 0.45 for ‘great’, 0.35 for ‘fair’, and 0.2 for ‘awful’.
B15: Decision alternative 1: Continue development and market the new product.
B16: Decision alternative 2: Stop development and abandon product
B18: Task 4a. Complete the tables below and the decision tree. | R18: Net revenue
K19: EMV ($M)
C20: Market
C21: Great | D21: Fair | E21: Awful
B22: Probability | C22: 0.45 | D22: 0.35 | E22: 0.2
B23: Sales volume ('000) | C23: 600 | D23: 300 | E23: 90
B24: Net revenue ($M)
B26: Payoff table
C27: States of nature (market)
B28: Decision alternatives | C28: Great | D28: Fair | E28: Awful | F28: EMV ($M)
B29: Continue development and market new product
B30: Stop development and abandon product
B32: Task 4b. Decide whether Acme should proceed with development

Sheet Acme 2
B2: Acme's two-stage new product decision.
B3: The decision tree below is from lecture slide 24.
B4: Task 5 is to calculate the EMVs listed in the table.
H7: Decision Tree
B8: Node | E8: EMV
B9: Sales volume | R9: Great | S9: 0.45
B10: Market product | S10: 10800
B11: Technological success
B12: Continue development
R13: Fair | S13: 0.35
S14: 5400
R16: Awful | S16: 0.2
S17: 1620
O21: No
P22: 0
N28: 0.2
N29: 0

Sheet Acme 3
B2: Task 6a. Write down the probabilities for stage 1 and stage 2 outcomes in the table below.
B3: Task 6b. Use your answers to part (a) to derive the probabilities in cells D10:D13.
B6: Risk profile of the best decisions (lecture slide 25)
E8: Probabilities
B9: Outcome | C9: Profit | D9: Probability | E9: Stage 1 outcome | F9: Stage 2 outcome
B10: Great sales volume | C10: $4.8M
B11: Fair sales demand | C11: -$0.60M
B12: Awful sales demand | C12: -$4.38M
B13: Isn’t a technological success | C13: -$4.00M
B14: Total | D14: 1

Sheet Sheet6
B7: Decision Alternatives | D7: Outcomes (Demand for a new facility)
D8: High | E8: Moderate | F8: Low
B9: Build a Fitness Centre with aquatics facilities | D9: 80000 | E9: 40000 | F9: -60000
B10: Build a Fitness Centre | D10: 45000 | E10: 25000 | F10: -10000
B11: Keep their business at its current size | D11: 10000 | E11: 5000 | F11: 0
B12: Probability | D12: 0.2 | E12: 0.5 | F12: 0.3
D13: 0.1 | E13: 0.5 | F13: =1-(D13+E13) -> 0.4
D14: 0.2 | E14: 0.5 | F14: =1-(D14+E14) -> 0.3
D15: 0.3 | E15: 0.5 | F15: =1-(D15+E15) -> 0.2
D16: 0.4 | E16: 0.5 | F16: =1-(D16+E16) -> 0.1
D17: 0.5 | E17: 0.5 | F17: =1-(D17+E17) -> 0

Sheet EX5
A1: Decision Trees - Provide a graphical view of the whole decision problem
